veda/tensors/cmake/FindVEDATensors.cmake
veda/tensors/include/veda/tensors/api.h
veda/tensors/include/veda/tensors/device.h
veda/tensors/include/veda/tensors/enums.h
veda/tensors/include/veda/tensors/get.h
veda/tensors/include/veda/tensors/high_level.h
veda/tensors/include/veda/tensors/init.h
veda/tensors/include/veda/tensors/low_level.h
veda/tensors/include/veda/tensors/macros.h
veda/tensors/include/veda/tensors/scalar.h
veda/tensors/include/veda/tensors/types.h
veda/tensors/include/veda/tensors/version.h
veda/tensors/lib64/libveda-tensors.so
veda/tensors/lib64/libveda-tensors.so.0
veda/tensors/lib64/libveda-tensors.so.0.1.8
veda/tensors/libve/libveda-tensors.vso
veda/tensors/libve/libveda-tensors.vso3
veda_tensors-0.1.8.dist-info/LICENSE
veda_tensors-0.1.8.dist-info/METADATA
veda_tensors-0.1.8.dist-info/top_list.txt
veda_tensors-0.1.8.dist-info/WHEEL
veda_tensors-0.1.8.dist-info/RECORD
