Metadata-Version: 2.1
Name: veda-tensors
Version: 0.1.8
Requires-Python: >=3.7
Summary: VEDA Tensors
Author: Nicolas Weber
Author-email: nicolas.weber@neclab.eu
Classifier: License :: OSI Approved :: BSD License
Classifier: Programming Language :: Python :: 3 :: Only
Classifier: Programming Language :: C
Classifier: Programming Language :: C++
Download-URL: https://github.com/sx-aurora/veda-tensors/tags
License: 3 BSD-License
Platform: linux_x86_x64
Requires-Dist: veda (>=2.2.1, <3)
Requires-Dist: tungl (>=0.1.4, <0.2)
